richreports/__init__.py
richreports/richreports.py
richreports-0.2.0.dist-info/LICENSE
richreports-0.2.0.dist-info/METADATA
richreports-0.2.0.dist-info/WHEEL
richreports-0.2.0.dist-info/top_level.txt
richreports-0.2.0.dist-info/RECORD
